mazesolver/__init__.py
mazesolver/__main__.py
mazesolver/create_final_image.py
mazesolver/g.py
mazesolver/load_maze.py
mazesolver/solve.py
mazesolver/strings.py
mazesolver-2.2.2.dist-info/LICENSE
mazesolver-2.2.2.dist-info/METADATA
mazesolver-2.2.2.dist-info/WHEEL
mazesolver-2.2.2.dist-info/entry_points.txt
mazesolver-2.2.2.dist-info/top_level.txt
mazesolver-2.2.2.dist-info/RECORD
