Metadata-Version: 2.1
Name: mazesolver
Version: 2.2.2
Summary: A shortest-path maze solving algorithm for image-based mazes.
Home-page: https://github.com/exciteabletom/mazesolver
Author: Tommy Dougiamas
Author-email: tom@digitalnook.net
License: UNKNOWN
Keywords: maze algorithm image solve
Platform: UNKNOWN
Classifier: License :: OSI Approved :: GNU General Public License v3 (GPLv3)
Classifier: Programming Language :: Python :: 3
Requires-Python: >=3.5
Requires-Dist: Pillow (>=6.0)
Requires-Dist: progress (>=1.5)
